numpy_frame/__init__.py
numpy_frame-0.1.0.dist-info/METADATA
numpy_frame-0.1.0.dist-info/WHEEL
numpy_frame-0.1.0.dist-info/licenses/LICENSE
numpy_frame-0.1.0.dist-info/RECORD
