Metadata-Version: 2.4
Name: numpy_frame
Version: 0.1.0
Summary: A lightweight wrapper around numpy arrays for DataFrame-like functionality
Project-URL: Homepage, https://github.com/mcargnel/numpy_frame
Author-email: Martin Cargnel <martincargnel@gmail.com>
License: MIT
License-File: LICENSE
Requires-Python: >=3.9
Requires-Dist: numpy>=1.20
